{
  "$schema": "https://schema.beckn.io/SupportAction/v2.0",
  "context": {
    "action": "beckn/support",
    "bapId": "food-app.example.com",
    "bapUri": "https://food-app.example.com/beckn",
    "bppId": "zomato.com",
    "bppUri": "https://zomato.com/beckn",
    "networkId": "beckn:retail-network:in",
    "version": "2.0.0",
    "ttl": "PT30S",
    "messageId": "supp-msg-009",
    "timestamp": "2026-03-10T16:30:00.000Z",
    "transactionId": "txn-0009-2026-dominos-pizza"
  },
  "message": {
    "supportRequest": {
      "@context": "https://schema.beckn.io/",
      "@type": "beckn:SupportRequest",
      "refId": "ord-2026031000009",
      "descriptor": {
        "@type": "beckn:Descriptor",
        "name": "Rider Unreachable",
        "shortDesc": "The delivery rider is not reachable and I cannot track"
      },
      "category": "RIDER_CONTACT",
      "consumer": {
        "@context": "https://schema.beckn.io/",
        "@type": "beckn:Consumer",
        "id": "ravi.kumar@food-app.example.com",
        "descriptor": {
          "@type": "beckn:Descriptor",
          "name": "Ravi Kumar"
        },
        "telephone": "+912109876543",
        "email": "ravi.kumar@example.com"
      }
    }
  }
}